OverloadingFixed/__init__.py
OverloadingFixed/_main/__init__.py
OverloadingFixed/_main/main.py
OverloadingFixed/_main/_funcs/__init__.py
OverloadingFixed/_main/_funcs/typing_funcs/__init__.py
OverloadingFixed/_main/_funcs/typing_funcs/main.py
OverloadingFixed/_main/_metaclasses/__init__.py
OverloadingFixed/_main/_metaclasses/GenericWrapperMeta/__init__.py
OverloadingFixed/_main/_metaclasses/GenericWrapperMeta/main.py
OverloadingFixed/_main/_metaclasses/GenericWrapperMeta-new/__init__.py
OverloadingFixed/_main/_metaclasses/GenericWrapperMeta-new/main.py
OverloadingFixed-1.11.dist-info/LICENSE
OverloadingFixed-1.11.dist-info/METADATA
OverloadingFixed-1.11.dist-info/WHEEL
OverloadingFixed-1.11.dist-info/top_level.txt
OverloadingFixed-1.11.dist-info/RECORD
