Metadata-Version: 2.1
Name: OverloadingFixed
Version: 1.11
Summary: Function overloading for Python 3
Home-page: https://github.com/toto112358/overloading.py
Author: L. Pham-Trong
Author-email: spam@lucasanss.xyz
License: UNKNOWN
Platform: UNKNOWN
Classifier: Programming Language :: Python :: 3
Classifier: License :: OSI Approved :: MIT License
Classifier: Operating System :: OS Independent
Requires-Python: >=3.0
